kmap/__init__.py
kmap/__main__.py
kmap/kMap.py
kmap/config/__init__.py
kmap/config/config.py
kmap/config/logging_default.ini
kmap/config/settings_default.ini
kmap/config/shortcut_default.ini
kmap/controller/__init__.py
kmap/controller/colormap.py
kmap/controller/crosshair.py
kmap/controller/crosshairannulus.py
kmap/controller/crosshairroi.py
kmap/controller/cubeoptions.py
kmap/controller/databasewindows.py
kmap/controller/dataslider.py
kmap/controller/filetab.py
kmap/controller/interpolation.py
kmap/controller/lmfitoptions.py
kmap/controller/lmfitorbitaloptions.py
kmap/controller/lmfitplot.py
kmap/controller/lmfitplottab.py
kmap/controller/lmfitresult.py
kmap/controller/lmfittab.py
kmap/controller/lmfittree.py
kmap/controller/lmfittreeitems.py
kmap/controller/mainwindow.py
kmap/controller/matplotlibwindow.py
kmap/controller/miniplots.py
kmap/controller/orbitaldatatab.py
kmap/controller/orbitaltable.py
kmap/controller/orbitaltablerow.py
kmap/controller/polarization.py
kmap/controller/profileplot.py
kmap/controller/profileplottab.py
kmap/controller/pyqtgraphplot.py
kmap/controller/realplotoptions.py
kmap/controller/renametabwindow.py
kmap/controller/slicedcubefileoptions.py
kmap/controller/sliceddatabaseoptions.py
kmap/controller/sliceddatabaseoptions2.py
kmap/controller/sliceddatatab.py
kmap/controller/splitviewoptions.py
kmap/controller/splitviewtab.py
kmap/controller/tabchoosewindow.py
kmap/controller/tabwidget.py
kmap/library/__init__.py
kmap/library/abstractdata.py
kmap/library/axis.py
kmap/library/colormap.py
kmap/library/database.py
kmap/library/id.py
kmap/library/misc.py
kmap/library/orbital.py
kmap/library/orbital2povray.py
kmap/library/orbitaldata.py
kmap/library/plotdata.py
kmap/library/qwidgetsub.py
kmap/library/sliceddata.py
kmap/model/__init__.py
kmap/model/colormap_model.py
kmap/model/crosshair_model.py
kmap/model/lmfit_model.py
kmap/model/lmfittab_model.py
kmap/model/mainwindow_model.py
kmap/model/matplotlibwindow_model.py
kmap-3.5.2.dist-info/LICENSE.md
kmap-3.5.2.dist-info/METADATA
kmap-3.5.2.dist-info/WHEEL
kmap-3.5.2.dist-info/top_level.txt
kmap-3.5.2.dist-info/RECORD
