Metadata-Version: 2.1
Name: kmap
Version: 3.5.2
Summary: Display, modify and analyse ARPES experiments and DFT       simulations.
Home-page: https://github.com/brands-d/kMap
Author: Dominik Brandstetter
Author-email: brandstetter.dominik@uni-graz.at
License: LGPL
License-File: LICENSE.md
Requires-Dist: h5py
Requires-Dist: scipy
Requires-Dist: matplotlib
Requires-Dist: pyside6!=6.9.*
Requires-Dist: numpy
Requires-Dist: pyopengl
Requires-Dist: lmfit
Requires-Dist: pyqtgraph>=0.13.3
Requires-Dist: scikit-image
